libgomp/__init__.py
libgomp-1.1.5.dist-info/licenses/LICENSE
libgomp-1.1.5.dist-info/METADATA
libgomp-1.1.5.dist-info/WHEEL
libgomp-1.1.5.dist-info/top_level.txt
libgomp-1.1.5.dist-info/RECORD
