Metadata-Version: 2.4
Name: libgomp
Version: 1.1.5
Summary: Safe PoC package for dependency confusion
License-File: LICENSE
Dynamic: license-file
Dynamic: summary
